xolobbbccca/__init__.py
xolobbbccca-1.0.dist-info/METADATA
xolobbbccca-1.0.dist-info/WHEEL
xolobbbccca-1.0.dist-info/top_level.txt
xolobbbccca-1.0.dist-info/RECORD
