Metadata-Version: 2.1
Name: xolobbbccca
Version: 1.0
Requires-Dist: requests
